{
  "date": "2026-04-21",
  "team_arr": 274072.70999999996,
  "team_quota": 447320,
  "team_wins": 147,
  "team_pipeline": 343829.09999999974,
  "team_open_deals": 172,
  "reps": {
    "Chris Byrnes": {
      "arr": 56616.96,
      "quota": 62000.0,
      "arr_pct": 91.31767741935484,
      "wins": 36,
      "demos": 40,
      "opps": 43,
      "opp_demo": 93.02329999999999,
      "opp_win": 83.7209,
      "demo_win": 90.0,
      "avg_arr_per_opp": 1572.69333333,
      "ss_opps": 35,
      "nbr_created": 6,
      "nbr_won": 3,
      "ec_units": 2,
      "ec_arr": 5988.0,
      "calls": 16,
      "conversations": 3,
      "emails_sent": 1,
      "emails_replied": 0
    },
    "Danny Martinez": {
      "arr": 21944.07,
      "quota": 55440.0,
      "arr_pct": 39.58165584415585,
      "wins": 11,
      "demos": 11,
      "opps": 24,
      "opp_demo": 45.8333,
      "opp_win": 45.8333,
      "demo_win": 100.0,
      "avg_arr_per_opp": 1994.91545455,
      "ss_opps": 18,
      "nbr_created": 0,
      "nbr_won": 1,
      "ec_units": 4,
      "ec_arr": 7739.07,
      "calls": 4,
      "conversations": 2,
      "emails_sent": 11,
      "emails_replied": 4
    },
    "Eleni Lembesis": {
      "arr": 19498.8,
      "quota": 55440.0,
      "arr_pct": 35.17099567099567,
      "wins": 11,
      "demos": 40,
      "opps": 39,
      "opp_demo": 1.025641,
      "opp_win": 28.205099999999998,
      "demo_win": 27.500000000000004,
      "avg_arr_per_opp": 1772.61818182,
      "ss_opps": 17,
      "nbr_created": 1,
      "nbr_won": 1,
      "ec_units": 2,
      "ec_arr": 3132.0,
      "calls": 19,
      "conversations": 6,
      "emails_sent": 158,
      "emails_replied": 1
    },
    "Jasmine Rieger": {
      "arr": 41042.4,
      "quota": 62000.0,
      "arr_pct": 66.19741935483871,
      "wins": 26,
      "demos": 34,
      "opps": 35,
      "opp_demo": 97.1429,
      "opp_win": 74.2857,
      "demo_win": 76.4706,
      "avg_arr_per_opp": 1578.55384615,
      "ss_opps": 22,
      "nbr_created": 8,
      "nbr_won": 3,
      "ec_units": 1,
      "ec_arr": 3450.0,
      "calls": 25,
      "conversations": 5,
      "emails_sent": 5,
      "emails_replied": 1
    },
    "Max Linder": {
      "arr": 50369.4,
      "quota": 55440.0,
      "arr_pct": 90.8538961038961,
      "wins": 16,
      "demos": 22,
      "opps": 27,
      "opp_demo": 81.4815,
      "opp_win": 59.2593,
      "demo_win": 72.7273,
      "avg_arr_per_opp": 3148.0875,
      "ss_opps": 10,
      "nbr_created": 6,
      "nbr_won": 1,
      "ec_units": 10,
      "ec_arr": 21264.0,
      "calls": 17,
      "conversations": 1,
      "emails_sent": 12,
      "emails_replied": 0
    },
    "Thomas Jensen": {
      "arr": 7323.36,
      "quota": 0.0,
      "arr_pct": 0.0,
      "wins": 6,
      "demos": 10,
      "opps": 24,
      "opp_demo": 41.6667,
      "opp_win": 25.0,
      "demo_win": 60.0,
      "avg_arr_per_opp": 1220.56,
      "ss_opps": 22,
      "nbr_created": 0,
      "nbr_won": 0,
      "ec_units": 2,
      "ec_arr": 2208.0,
      "calls": 1,
      "conversations": 0,
      "emails_sent": 1,
      "emails_replied": 0
    },
    "Tyler Stevens": {
      "arr": 77277.72,
      "quota": 95000.0,
      "arr_pct": 81.34496842105263,
      "wins": 41,
      "demos": 60,
      "opps": 67,
      "opp_demo": 89.5522,
      "opp_win": 61.194,
      "demo_win": 68.3333,
      "avg_arr_per_opp": 1884.82243902,
      "ss_opps": 53,
      "nbr_created": 5,
      "nbr_won": 4,
      "ec_units": 14,
      "ec_arr": 20229.6,
      "calls": 0,
      "conversations": 0,
      "emails_sent": 0,
      "emails_replied": 0
    }
  }
}