{
  "parent": "Busy Bee - Parent Account",
  "slug": "busy-bee",
  "total_headroom": "$45,660",
  "non_ec_headroom": "$41,880",
  "est_ec_headroom": "$3,780",
  "employee_count": "23",
  "non_ec_arr": "$6,900",
  "state": "FL",
  "city": "Pinellas Park",
  "restaurant_type": "Cafe/Bakery/Dessert",
  "contact_email": "agori25@aol.com",
  "location_count": 2,
  "location_names": [
    "Busy Bee",
    "Busy Bee 2"
  ],
  "websites": [
    "https://busybeediner.com/"
  ],
  "website_discovery_status": "found",
  "fingerprints": {
    "https://busybeediner.com/": {
      "url": "https://busybeediner.com/",
      "html_bytes": 177028,
      "fingerprints": {
        "website_cms": "WordPress",
        "marketing": "Mailchimp"
      },
      "toast": {}
    },
    "https://busybeediner.com/menu-item/texan-omelet/": {
      "url": "https://busybeediner.com/menu-item/texan-omelet/",
      "html_bytes": 47735,
      "fingerprints": {
        "website_cms": "WordPress",
        "marketing": "Mailchimp"
      },
      "toast": {}
    },
    "https://busybeediner.com/menu-item/vegetarian-omelet/": {
      "url": "https://busybeediner.com/menu-item/vegetarian-omelet/",
      "html_bytes": 47816,
      "fingerprints": {
        "website_cms": "WordPress",
        "marketing": "Mailchimp"
      },
      "toast": {}
    },
    "https://busybeediner.com/menu-item/buttermilk-pancakes/": {
      "url": "https://busybeediner.com/menu-item/buttermilk-pancakes/",
      "html_bytes": 47806,
      "fingerprints": {
        "website_cms": "WordPress",
        "marketing": "Mailchimp"
      },
      "toast": {}
    },
    "https://busybeediner.com/menu-item/blueberry-or-chocolate-chip-pancakes/": {
      "url": "https://busybeediner.com/menu-item/blueberry-or-chocolate-chip-pancakes/",
      "html_bytes": 48157,
      "fingerprints": {
        "website_cms": "WordPress",
        "marketing": "Mailchimp"
      },
      "toast": {}
    },
    "https://busybeediner.com/menu-item/belgian-waffle/": {
      "url": "https://busybeediner.com/menu-item/belgian-waffle/",
      "html_bytes": 47805,
      "fingerprints": {
        "website_cms": "WordPress",
        "marketing": "Mailchimp"
      },
      "toast": {}
    },
    "https://busybeediner.com/menu-item/busy-bee-222-breakfast/": {
      "url": "https://busybeediner.com/menu-item/busy-bee-222-breakfast/",
      "html_bytes": 48029,
      "fingerprints": {
        "website_cms": "WordPress",
        "marketing": "Mailchimp"
      },
      "toast": {}
    }
  },
  "toast_products": {},
  "marketplaces": {},
  "marketplaces_status": "pending",
  "hr_vendor": "",
  "hr_status": "pending",
  "notes": []
}