{
  "parent": "Frankies Rawbar Parent",
  "slug": "frankies-rawbar",
  "total_headroom": "$22,200",
  "non_ec_headroom": "$20,940",
  "est_ec_headroom": "$1,260",
  "employee_count": "8",
  "non_ec_arr": "$962",
  "state": "FL",
  "city": "New Port Richey",
  "restaurant_type": "FSR - Casual",
  "contact_email": "rrawbar@tampabay.rr.com",
  "location_count": 1,
  "location_names": [
    "Frankies Rawbar"
  ],
  "websites": [
    "https://frankiesrawbar.com/"
  ],
  "website_discovery_status": "found",
  "fingerprints": {
    "https://frankiesrawbar.com/": {
      "url": "https://frankiesrawbar.com/",
      "html_bytes": 119804,
      "fingerprints": {
        "website_cms": "WordPress"
      },
      "toast": {}
    },
    "https://frankiesrawbar.com/menu-2/": {
      "url": "https://frankiesrawbar.com/menu-2/",
      "html_bytes": 92712,
      "fingerprints": {
        "website_cms": "WordPress"
      },
      "toast": {}
    }
  },
  "toast_products": {},
  "marketplaces": [
    "doordash"
  ],
  "marketplaces_status": "done",
  "hr_vendor": "",
  "hr_status": "pending",
  "notes": [],
  "reps": [
    "byrnes"
  ],
  "sfdc_account_id": "0013c00001tGzZoAAK"
}