{
  "parent": "Hurricane Hanks Parent",
  "slug": "hurricane-hanks",
  "total_headroom": "$20,340",
  "non_ec_headroom": "$20,340",
  "est_ec_headroom": "$0",
  "employee_count": "11",
  "non_ec_arr": "$1,200",
  "state": "FL",
  "city": "Holmes Beach",
  "restaurant_type": "Cafe/Bakery/Dessert",
  "contact_email": "brian.mathae@me.com",
  "location_count": 1,
  "location_names": [
    "Fifty Three Fifty Pourhouse"
  ],
  "websites": [
    "https://hurricanehanks.com/"
  ],
  "website_discovery_status": "found",
  "fingerprints": {
    "https://hurricanehanks.com/": {
      "url": "https://hurricanehanks.com/",
      "html_bytes": 292683,
      "fingerprints": {
        "website_cms": "Squarespace",
        "marketing": "Mailchimp"
      },
      "toast": {}
    }
  },
  "toast_products": {},
  "marketplaces": [],
  "marketplaces_status": "done",
  "hr_vendor": "",
  "hr_status": "pending",
  "notes": [],
  "reps": [
    "byrnes"
  ],
  "sfdc_account_id": "0014W00002V1ts6QAB"
}