{
  "parent": "Post Industries, LLC",
  "slug": "post-industries-llc",
  "total_headroom": "$12,624",
  "non_ec_headroom": "$12,624",
  "est_ec_headroom": "$0",
  "employee_count": "4",
  "non_ec_arr": "$10,404",
  "state": "FL",
  "city": "Tampa",
  "restaurant_type": "Pizzeria",
  "contact_email": "joseph.harris17@icloud.com",
  "location_count": 1,
  "location_names": [
    "Gourmet Pizza Co."
  ],
  "websites": [
    "https://gourmetpizzacompany.com"
  ],
  "website_discovery_status": "found",
  "fingerprints": {
    "https://gourmetpizzacompany.com": {
      "url": "https://gourmetpizzacompany.com",
      "html_bytes": 176581,
      "fingerprints": {
        "website_cms": "SpotHopper",
        "oo": "Toast OO (native)",
        "catering_mention": "Catering page"
      },
      "toast": {
        "toast_oo_native": "order.toasttab.com/online/gourmetpizzaco",
        "toast_oo_whitelabel_host": "https://order.toasttab.com/"
      }
    }
  },
  "toast_products": {
    "toast_oo_native": "order.toasttab.com/online/gourmetpizzaco",
    "toast_oo_whitelabel_host": "https://order.toasttab.com/"
  },
  "marketplaces": [
    "doordash",
    "ubereats",
    "grubhub",
    "slicelife"
  ],
  "marketplaces_status": "done",
  "hr_vendor": "",
  "hr_status": "pending",
  "notes": [],
  "reps": [
    "byrnes"
  ],
  "sfdc_account_id": "0014W00003JTuxZQAT"
}