{
  "parent": "St. Pete Hospitality Group",
  "slug": "st-pete-hospitality-group",
  "total_headroom": "$48,276",
  "non_ec_headroom": "$48,276",
  "est_ec_headroom": "$0",
  "employee_count": "209",
  "non_ec_arr": "$48,340",
  "state": "FL",
  "city": "St Petersburg",
  "restaurant_type": "Cafe/Bakery/Dessert",
  "contact_email": "cbandel@thedali.org",
  "location_count": 3,
  "location_names": [
    "Cafe Gala",
    "Parkshore Grill",
    "The Island Grille & Raw Bar"
  ],
  "websites": [
    "https://stpetehospitalitygroup.com/"
  ],
  "website_discovery_status": "found",
  "fingerprints": {
    "https://stpetehospitalitygroup.com/": {
      "url": "https://stpetehospitalitygroup.com/",
      "html_bytes": 193850,
      "fingerprints": {
        "website_cms": "WordPress"
      },
      "toast": {}
    }
  },
  "toast_products": {},
  "marketplaces": [],
  "marketplaces_status": "done",
  "hr_vendor": "",
  "hr_status": "pending",
  "notes": [],
  "reps": [
    "byrnes"
  ]
}